setup.py
CodeMommy/WebPython.py
CodeMommy/core/About.py
CodeMommy/core/Http.py
CodeMommy/core/Output.py
CodeMommy/core/Route.py
CodeMommy/core/Server.py
CodeMommyWebPython.egg-info/PKG-INFO
CodeMommyWebPython.egg-info/SOURCES.txt
CodeMommyWebPython.egg-info/dependency_links.txt
CodeMommyWebPython.egg-info/requires.txt
CodeMommyWebPython.egg-info/top_level.txt
CodeMommy/core/About.py
CodeMommy/core/Http.py
CodeMommy/core/Output.py
CodeMommy/core/Route.py
CodeMommy/core/Server.py