Metadata-Version: 1.0
Name: CodeMommyWebPython
Version: 0.0.3
Summary: CodeMommy WebPython is a light, fast, free and open source Python MVC framework.
Home-page: http://www.CodeMommy.com
Author: Candison
Author-email: kandisheng@163.com
License: Apache 2.0
Platform: Any
